<?xml version='1.0' encoding='UTF-8'?>
<?compositeArtifactRepository version='1.0.0'?>
<repository name='ContextMapper DSL Composite Site 6.11.x' type='org.eclipse.equinox.internal.p2.artifact.repository.CompositeArtifactRepository' version='1.0.0'>
  <properties size='2'>
    <property name='p2.timestamp' value='1724412231684'/>
    <property name='p2.atomic.composite.loading' value='false'/>
  </properties>
  <children size='13'>
    <child location='../../../releases/6.11.0.202401111213'/>
    <child location='../../../releases/6.11.1.202401111223'/>
    <child location='../../../releases/6.11.1.202408091420'/>
    <child location='../../../releases/6.11.1.202408091456'/>
    <child location='../../../releases/6.11.1.202408131103'/>
    <child location='../../../releases/6.11.1.202408131210'/>
    <child location='../../../releases/6.11.1.202408131421'/>
    <child location='../../../releases/6.11.1.202408151443'/>
    <child location='../../../releases/6.11.1.202408151616'/>
    <child location='../../../releases/6.11.1.202408211810'/>
    <child location='../../../releases/6.11.1.202408221426'/>
    <child location='../../../releases/6.11.1.202408230822'/>
    <child location='../../../releases/6.11.1.202408231121'/>
  </children>
</repository>
